{
"type": "FeatureCollection",
"name": "TODO_points",
"crs": { "type": "name", "properties": { "name": "urn:ogc:def:crs:OGC:1.3:CRS84" } },
"features": [
{ "type": "Feature", "properties": { "HUC8": "07100007", "P02a_Assign": null, "P01_MM": "7/30/2023", "Name": "South Raccoon", "RAW_Grd_MM": "2023/08/31", "DFIRM_Grd_MM": "", "Addl_Grd_MM": "", "Prod Stage": "Phase 1", "P01 Analyst": "YES", "AECOM Tie-in": null, "TO_Area": "FY21_2A", "Model Complete": "6/11/2023", "Notes": "TODO: RAW, DRAFT, Addl", "which_grid": "1, 2", "Addl_Gri_1": "", "BFE_TODO_F": "T", "Contract_1": null, "DFIRM_Gr_1": "", "Final_Mo_1": "2023/06/11", "FRP_First": null, "Grids_No_1": "TODO: RAW, DRAFT, Addl", "huc8_First": "07100007", "Mapping__1": "YES", "name_First": "South Raccoon", "PBL_Assi_1": null, "Phase_1__1": "2023/07/30", "Producti_1": "Phase 1", "RAW_Grid_F": "2023/08/31", "TO_Area_Fi": "FY21_2A", "which_gr_1": "1, 2" }, "geometry": { "type": "Point", "coordinates": [ -94.596303973562854, 41.839949271492145 ] } },
{ "type": "Feature", "properties": { "HUC8": "10230003", "P02a_Assign": "RK", "P01_MM": "8/5/2024", "Name": "Little Sioux", "RAW_Grd_MM": "2024/08/07", "DFIRM_Grd_MM": "", "Addl_Grd_MM": "", "Prod Stage": "DD Mapping", "P01 Analyst": "E + M", "AECOM Tie-in": null, "TO_Area": "FY22_3B", "Model Complete": "7/16/2024", "Notes": "TODO: PBL, BFE, Validation", "which_grid": "1, 2", "Addl_Gri_1": "", "BFE_TODO_F": "F", "Contract_1": null, "DFIRM_Gr_1": "", "Final_Mo_1": "2024/07/16", "FRP_First": null, "Grids_No_1": "TODO: PBL, BFE, Validation", "huc8_First": "10230003", "Mapping__1": "E + M", "name_First": "Little Sioux", "PBL_Assi_1": "RK", "Phase_1__1": "2024/08/05", "Producti_1": "DD Mapping", "RAW_Grid_F": "2024/08/07", "TO_Area_Fi": "FY22_3B", "which_gr_1": "1, 2" }, "geometry": { "type": "Point", "coordinates": [ -95.659233170752771, 42.638963937721883 ] } },
{ "type": "Feature", "properties": { "HUC8": "10230007", "P02a_Assign": "MT", "P01_MM": "7/30/2024", "Name": "Boyer", "RAW_Grd_MM": "2024/07/30", "DFIRM_Grd_MM": "", "Addl_Grd_MM": "", "Prod Stage": "DD Mapping", "P01 Analyst": "Reina", "AECOM Tie-in": null, "TO_Area": "FY22_3B", "Model Complete": "7/21/2024", "Notes": "TODO: PBL, BFE, Validation", "which_grid": "1, 2", "Addl_Gri_1": "", "BFE_TODO_F": "F", "Contract_1": null, "DFIRM_Gr_1": "", "Final_Mo_1": "2024/07/21", "FRP_First": null, "Grids_No_1": "TODO: PBL, BFE, Validation", "huc8_First": "10230007", "Mapping__1": "Reina", "name_First": "Boyer", "PBL_Assi_1": "MT", "Phase_1__1": "2024/07/30", "Producti_1": "DD Mapping", "RAW_Grid_F": "2024/07/30", "TO_Area_Fi": "FY22_3B", "which_gr_1": "1, 2" }, "geometry": { "type": "Point", "coordinates": [ -95.336536044888376, 42.02676843924668 ] } },
{ "type": "Feature", "properties": { "HUC8": "07060005", "P02a_Assign": "EC", "P01_MM": "2/28/2024", "Name": "Apple-Plum", "RAW_Grd_MM": "2024/04/04", "DFIRM_Grd_MM": "2024/04/05", "Addl_Grd_MM": "2024/04/05", "Prod Stage": "Pass 2/2", "P01 Analyst": "Erika", "AECOM Tie-in": null, "TO_Area": "FY20_1A", "Model Complete": "1/10/2024", "Notes": "TODO: Missing 0.2% Vel grid", "which_grid": "All on MM", "Addl_Gri_1": "2024/04/05", "BFE_TODO_F": "F", "Contract_1": null, "DFIRM_Gr_1": "2024/04/05", "Final_Mo_1": "2024/01/10", "FRP_First": "CSLF; PAC; Velocity", "Grids_No_1": "TODO: Missing 0.2% Vel grid", "huc8_First": "07060005", "Mapping__1": "Erika", "name_First": "Apple-Plum", "PBL_Assi_1": "EC", "Phase_1__1": "2024/02/28", "Producti_1": "Pass 2/2", "RAW_Grid_F": "2024/04/04", "TO_Area_Fi": "FY20_1A", "which_gr_1": "All on MM" }, "geometry": { "type": "Point", "coordinates": [ -90.446771270999406, 42.210686605176278 ] } }
]
}
