{
"type": "FeatureCollection",
"name": "TODO_points",
"crs": { "type": "name", "properties": { "name": "urn:ogc:def:crs:OGC:1.3:CRS84" } },
"features": [
{ "type": "Feature", "properties": { "HUC8": "07060001", "which_grid": "1, 2", "Name": "Coon-Yellow", "PBL_Assign": "QB", "P01_MM": "2023/11/30", "RAW_Grd_MM": "2024/02/23", "DFIRM_Grd_MM": "0000/00/00", "Addl_Grd_MM": "0000/00/00", "Prod Stage": "Phase 1 Delivered", "P01 Analyst": "Matt", "AECOM Tie-in": "NO", "Name__HUC8": "Coon-Yellow", "TO_Area": "FY20_1A", "Model Complete": "2023/10/12", "Contractor": "AtkinsRealis", "loc_id": 1.0, "Grid Notes": "TODO: DRAFT, Addl Grids" }, "geometry": { "type": "Point", "coordinates": [ -91.337021679114656, 43.241926444503747 ] } },
{ "type": "Feature", "properties": { "HUC8": "07060002", "which_grid": "2", "Name": "Upper Iowa", "PBL_Assign": "MB", "P01_MM": "2023/11/30", "RAW_Grd_MM": "2024/02/23", "DFIRM_Grd_MM": "2024/03/10", "Addl_Grd_MM": "0000/00/00", "Prod Stage": "Phase 1 Delivered", "P01 Analyst": "Reina", "AECOM Tie-in": "NO", "Name__HUC8": "Upper Iowa", "TO_Area": "FY20_1A", "Model Complete": "2023/10/12", "Contractor": "AtkinsRealis", "loc_id": 2.0, "Grid Notes": "TODO: DRAFT, Addl Grids" }, "geometry": { "type": "Point", "coordinates": [ -91.719612268863727, 43.333689836502415 ] } },
{ "type": "Feature", "properties": { "HUC8": "07100007", "which_grid": "1, 2", "Name": "South Raccoon", "PBL_Assign": null, "P01_MM": "2023/07/30", "RAW_Grd_MM": "2023/08/31", "DFIRM_Grd_MM": "0000/00/00", "Addl_Grd_MM": "0000/00/00", "Prod Stage": "Phase 1 Delivered", "P01 Analyst": "YES", "AECOM Tie-in": "YES", "Name__HUC8": "South Raccoon", "TO_Area": "FY21_2A", "Model Complete": "2023/06/11", "Contractor": "AtkinsRealis", "loc_id": 10.0, "Grid Notes": "TODO: RAW, DRAFT, Addl" }, "geometry": { "type": "Point", "coordinates": [ -94.596311694417508, 41.839956700500068 ] } },
{ "type": "Feature", "properties": { "HUC8": "07080201", "which_grid": "2", "Name": "Upper Cedar", "PBL_Assign": "RK", "P01_MM": "2023/12/30", "RAW_Grd_MM": "2024/03/15", "DFIRM_Grd_MM": "2024/08/15", "Addl_Grd_MM": "0000/00/00", "Prod Stage": "Phase 1 Delivered", "P01 Analyst": "Matt", "AECOM Tie-in": "YES", "Name__HUC8": "Upper Cedar", "TO_Area": "FY20_1A", "Model Complete": "2023/11/11", "Contractor": "AtkinsRealis", "loc_id": 19.0, "Grid Notes": "UPDATE: DFIRM, TODO: Add'l" }, "geometry": { "type": "Point", "coordinates": [ -92.603922692530972, 43.050848225000038 ] } }
]
}
